PyIpCom.py
PyIpCom-1.0.dist-info/METADATA
PyIpCom-1.0.dist-info/WHEEL
PyIpCom-1.0.dist-info/top_level.txt
PyIpCom-1.0.dist-info/RECORD
