Metadata-Version: 2.1
Name: PyIpCom
Version: 1.0
Summary: UNKNOWN
Home-page: UNKNOWN
Author: Himanshu Jha
Author-email: UNKNOWN
License: UNKNOWN
Platform: UNKNOWN
Requires-Dist: PyGithub
